py.typed
scraper_rs.pyi
scraper_rs/__init__.py
scraper_rs/asyncio.py
scraper_rs/asyncio.pyi
scraper_rs/scraper_rs.cp314t-win_amd64.pyd
scraper_rust-0.2.27.dist-info/METADATA
scraper_rust-0.2.27.dist-info/WHEEL
scraper_rust-0.2.27.dist-info/licenses/LICENSE
scraper_rust-0.2.27.dist-info/RECORD
