Metadata-Version: 2.4
Name: scraper-rust
Version: 0.2.27
Classifier: Programming Language :: Python
Classifier: Programming Language :: Python :: 3
Classifier: Programming Language :: Python :: 3 :: Only
Classifier: Programming Language :: Rust
Classifier: Programming Language :: Python :: 3.10
Classifier: Programming Language :: Python :: 3.11
Classifier: Programming Language :: Python :: 3.12
Classifier: Programming Language :: Python :: 3.13
Classifier: Programming Language :: Python :: 3.14
Classifier: Typing :: Typed
Requires-Dist: maturin ; extra == 'dev'
Requires-Dist: pytest ; extra == 'dev'
Provides-Extra: dev
License-File: LICENSE
Summary: Python bindings around rust-scraper/scraper with PyO3
Keywords: html,scraping,css selectors,xpath,pyo3,rust
Author-email: Yehor Smoliakov <egorsmkv@gmail.com>
Requires-Python: >=3.10
Project-URL: Homepage, https://github.com/RustedBytes/scraper-rs
Project-URL: Documentation, https://github.com/RustedBytes/scraper-rs#readme
Project-URL: Repository, https://github.com/RustedBytes/scraper-rs
Project-URL: Issues, https://github.com/RustedBytes/scraper-rs/issues
